auth/_init__.py
auth/client.py
auth/exceptions.py
discussion/exceptions.py
discussion/manager.py
django/discussion.py
django/e2b_example.py
django/e2b_integration.py
django/e2b_urls.py
django/workflow_example.py
e2b_interpreter/__init__.py
e2b_interpreter/client.py
e2b_interpreter/exceptions.py
e2b_interpreter/tests.py
fastapi/e2b_example.py
fastapi/e2b_integration.py
fastapi/example.py
fastapi/middleware.py
fastapi/security.py
fastapi/workflow_example.py
generators/base.py
generators/django.py
generators/fastapi.py
utils/templates.py
workflows/__init__.py
workflows/exceptions.py
workflows/manager.py
workflows/models.py
composio_integration_frameworks-0.1.0.dist-info/LICENSE
composio_integration_frameworks-0.1.0.dist-info/METADATA
composio_integration_frameworks-0.1.0.dist-info/WHEEL
composio_integration_frameworks-0.1.0.dist-info/entry_points.txt
composio_integration_frameworks-0.1.0.dist-info/top_level.txt
composio_integration_frameworks-0.1.0.dist-info/RECORD
