Metadata-Version: 2.2
Name: composio_integration_frameworks
Version: 0.1.0
Summary: Integrate Composio's AgentAuth with FastAPI and Django
Home-page: https://github.com/Frontier-tech-consulting/composio_integration_frameworks
Author: Dhruv Malik
Author-email: Dhruv Malik <malikdhruv1994@gmail.com>
License: MIT
Project-URL: Homepage, https://github.com/Frontier-tech-consulting/composio_integration_frameworks
Project-URL: Documentation, https://github.com/Frontier-tech-consulting/composio_integration_frameworks#readme
Project-URL: Repository, https://github.com/Frontier-tech-consulting/composio_integration_frameworks.git
Project-URL: Issues, https://github.com/Frontier-tech-consulting/composio_integration_frameworks/issues
Keywords: composio,agents,ai,authentication,vector database,django,fastapi,code interpreter,e2b,workflow
Classifier: Development Status :: 3 - Alpha
Classifier: Intended Audience :: Developers
Classifier: License :: OSI Approved :: MIT License
Classifier: Programming Language :: Python :: 3
Classifier: Programming Language :: Python :: 3.8
Classifier: Programming Language :: Python :: 3.9
Classifier: Programming Language :: Python :: 3.10
Classifier: Framework :: Django
Classifier: Framework :: FastAPI
Classifier: Topic :: Software Development :: Libraries :: Python Modules
Classifier: Operating System :: OS Independent
Requires-Python: >=3.8,<3.11
License-File: LICENSE
Requires-Dist: requests>=2.28.0
Requires-Dist: composio>=0.1.0
Provides-Extra: fastapi
Requires-Dist: fastapi>=0.100.0; extra == "fastapi"
Requires-Dist: pydantic>=2.0.0; extra == "fastapi"
Requires-Dist: uvicorn>=0.15.0; extra == "fastapi"
Provides-Extra: django
Requires-Dist: django>=4.0; extra == "django"
Provides-Extra: pinecone
Requires-Dist: pinecone-client>=2.0.0; extra == "pinecone"
Provides-Extra: chroma
Requires-Dist: chromadb>=0.3.24; extra == "chroma"
Provides-Extra: langchain
Requires-Dist: langchain>=0.0.248; extra == "langchain"
Provides-Extra: crewai
Requires-Dist: crewai>=0.0.1; extra == "crewai"
Provides-Extra: e2b
Requires-Dist: e2b-code-interpreter>=0.1.0; extra == "e2b"
Provides-Extra: test
Requires-Dist: pytest>=7.0.0; extra == "test"
Requires-Dist: pytest-asyncio>=0.18.0; extra == "test"
Requires-Dist: httpx>=0.23.0; extra == "test"
Provides-Extra: all
Requires-Dist: fastapi>=0.100.0; extra == "all"
Requires-Dist: pydantic>=2.0.0; extra == "all"
Requires-Dist: uvicorn>=0.15.0; extra == "all"
Requires-Dist: django>=4.0; extra == "all"
Requires-Dist: pinecone-client>=2.0.0; extra == "all"
Requires-Dist: chromadb>=0.3.24; extra == "all"
Requires-Dist: langchain>=0.0.248; extra == "all"
Requires-Dist: crewai>=0.0.1; extra == "all"
Requires-Dist: e2b-code-interpreter>=0.1.0; extra == "all"
Requires-Dist: pytest>=7.0.0; extra == "all"
Requires-Dist: pytest-asyncio>=0.18.0; extra == "all"
Requires-Dist: httpx>=0.23.0; extra == "all"
Dynamic: author
Dynamic: home-page
Dynamic: requires-python
